ipymonaco/__init__.py
ipymonaco/_version.py
ipymonaco/editor.py
ipymonaco/static/b3726f0165bf67ac68494ee7a1b9f6ce.ttf
ipymonaco/static/css.worker.js
ipymonaco/static/css.worker.js.map
ipymonaco/static/editor.worker.js
ipymonaco/static/editor.worker.js.map
ipymonaco/static/extension.js
ipymonaco/static/html.worker.js
ipymonaco/static/html.worker.js.map
ipymonaco/static/index.js
ipymonaco/static/index.js.map
ipymonaco/static/json.worker.js
ipymonaco/static/json.worker.js.map
ipymonaco/static/ts.worker.js
ipymonaco/static/ts.worker.js.map
ipymonaco-0.0.23a0.data/data/etc/jupyter/nbconfig/notebook.d/ipymonaco.json
ipymonaco-0.0.23a0.data/data/share/jupyter/nbextensions/ipymonaco/b3726f0165bf67ac68494ee7a1b9f6ce.ttf
ipymonaco-0.0.23a0.data/data/share/jupyter/nbextensions/ipymonaco/css.worker.js
ipymonaco-0.0.23a0.data/data/share/jupyter/nbextensions/ipymonaco/css.worker.js.map
ipymonaco-0.0.23a0.data/data/share/jupyter/nbextensions/ipymonaco/editor.worker.js
ipymonaco-0.0.23a0.data/data/share/jupyter/nbextensions/ipymonaco/editor.worker.js.map
ipymonaco-0.0.23a0.data/data/share/jupyter/nbextensions/ipymonaco/extension.js
ipymonaco-0.0.23a0.data/data/share/jupyter/nbextensions/ipymonaco/html.worker.js
ipymonaco-0.0.23a0.data/data/share/jupyter/nbextensions/ipymonaco/html.worker.js.map
ipymonaco-0.0.23a0.data/data/share/jupyter/nbextensions/ipymonaco/index.js
ipymonaco-0.0.23a0.data/data/share/jupyter/nbextensions/ipymonaco/index.js.map
ipymonaco-0.0.23a0.data/data/share/jupyter/nbextensions/ipymonaco/json.worker.js
ipymonaco-0.0.23a0.data/data/share/jupyter/nbextensions/ipymonaco/json.worker.js.map
ipymonaco-0.0.23a0.data/data/share/jupyter/nbextensions/ipymonaco/ts.worker.js
ipymonaco-0.0.23a0.data/data/share/jupyter/nbextensions/ipymonaco/ts.worker.js.map
ipymonaco-0.0.23a0.dist-info/LICENSE
ipymonaco-0.0.23a0.dist-info/METADATA
ipymonaco-0.0.23a0.dist-info/WHEEL
ipymonaco-0.0.23a0.dist-info/top_level.txt
ipymonaco-0.0.23a0.dist-info/RECORD
